{
  "groups": [
    [],
    [],
    [],
    [],
    [],
    [],
    [],
    [],
    [],
    [],
    [
      {
        "label": "ColorSelects_TxtLayerA",
        "text": "Layer A"
      }
    ],
    [
      {
        "label": "ColorSelects_TxtLayerB",
        "text": "Layer B"
      }
    ],
    [
      {
        "label": "ColorSelects_TxtCL",
        "text": "C"
      },
      {
        "label": "ColorSelects_TxtLayerC",
        "text": "Layer C"
      }
    ],
    [],
    [],
    [],
    [],
    [],
    [],
    [],
    [],
    [],
    [
      {
        "label": "ColorSelects_TxtMergeBtA",
        "text": "B + A Combination"
      }
    ],
    [],
    [
      {
        "label": "ColorSelects_TxtMergeBtC",
        "text": "B + C Combination"
      }
    ],
    [],
    [],
    [],
    [],
    [],
    [],
    [],
    [],
    [],
    [],
    [],
    [],
    [],
    [
      {
        "label": "ColorSelects_TxtA",
        "text": "A"
      }
    ],
    [
      {
        "label": "ColorSelects_TxtB",
        "text": "B"
      }
    ],
    [
      {
        "label": "ColorSelects_TxtC",
        "text": "C"
      }
    ],
    [],
    [],
    [],
    [],
    [],
    [],
    [],
    [],
    [],
    [],
    [],
    [],
    [],
    [
      {
        "label": "ColorSelects_TxtMergeA",
        "text": "A + B + C Combination"
      },
      {
        "label": "ColorSelects_TxtBL",
        "text": "B"
      }
    ],
    [
      {
        "label": "ColorSelects_TxtMergeB",
        "text": "A + B + C Combination"
      }
    ],
    [
      {
        "label": "ColorSelects_TxtMergeC",
        "text": "A + B + C Combination"
      }
    ],
    [],
    [],
    [],
    [],
    [],
    [],
    [],
    [],
    [],
    [],
    [],
    [],
    [
      {
        "label": "ColorSelects_TxtMergeCtA",
        "text": "C + A Combination"
      }
    ],
    [
      {
        "label": "ColorSelects_TxtMergeCtB",
        "text": "C + B Combination"
      }
    ],
    [],
    [],
    [],
    [],
    [],
    [],
    [
      {
        "label": "ColorSelects_TxtMergeAtB",
        "text": "A + B Combination"
      }
    ],
    [
      {
        "label": "ColorSelects_TxtMergeAtC",
        "text": "A + C Combination"
      }
    ],
    [],
    [],
    [],
    [],
    [],
    [],
    [],
    [],
    [],
    [],
    [],
    [],
    [],
    [],
    [],
    [],
    [],
    [
      {
        "label": "ColorSelects_TxtAL",
        "text": "A"
      }
    ],
    [],
    [],
    [],
    []
  ]
}