{
  "groups": [
    [],
    [],
    [],
    [],
    [],
    [],
    [],
    [],
    [],
    [],
    [],
    [],
    [],
    [],
    [],
    [],
    [],
    [],
    [],
    [],
    [],
    [],
    [],
    [
      {
        "label": "Select_TxtPaintFlip",
        "text": "Invertir colores"
      }
    ],
    [],
    [],
    [],
    [],
    [],
    [
      {
        "label": "Select_TxtCopy",
        "text": "Copiar"
      }
    ],
    [],
    [],
    [],
    [],
    [],
    [],
    [],
    [],
    [],
    [],
    [],
    [],
    [],
    [],
    [],
    [],
    [],
    [],
    [],
    [],
    [],
    [],
    [],
    [],
    [],
    [],
    [],
    [],
    [],
    [],
    [],
    [],
    [],
    [],
    [],
    [],
    [],
    [
      {
        "label": "Select_TxtOutLine",
        "text": "Contorno"
      }
    ],
    [],
    [],
    [],
    [
      {
        "label": "Select_TxtPaint",
        "text": "Guardar como patrón "
      }
    ],
    [
      {
        "label": "Select_TxtPaste",
        "text": "Pegar"
      }
    ],
    [],
    [],
    [],
    [],
    [],
    [],
    [],
    [],
    [],
    [],
    [],
    [],
    [],
    [],
    [],
    [],
    [],
    [],
    [],
    [],
    [],
    [],
    [],
    [],
    [],
    [
      {
        "label": "Select_TxtColorFlip",
        "text": "Transformar colores"
      }
    ],
    [],
    []
  ]
}